jleechanorg_pr_automation/STORAGE_STATE_TESTING_PROTOCOL.md
jleechanorg_pr_automation/__init__.py
jleechanorg_pr_automation/automation_safety_manager.py
jleechanorg_pr_automation/automation_safety_wrapper.py
jleechanorg_pr_automation/automation_utils.py
jleechanorg_pr_automation/check_codex_comment.py
jleechanorg_pr_automation/codex_branch_updater.py
jleechanorg_pr_automation/codex_config.py
jleechanorg_pr_automation/jleechanorg_pr_monitor.py
jleechanorg_pr_automation/logging_utils.py
jleechanorg_pr_automation/orchestrated_pr_runner.py
jleechanorg_pr_automation/utils.py
jleechanorg_pr_automation/openai_automation/__init__.py
jleechanorg_pr_automation/openai_automation/codex_github_mentions.py
jleechanorg_pr_automation/openai_automation/debug_page_content.py
jleechanorg_pr_automation/openai_automation/oracle_cli.py
jleechanorg_pr_automation/openai_automation/test_auth_restoration.py
jleechanorg_pr_automation/openai_automation/test_codex_comprehensive.py
jleechanorg_pr_automation/openai_automation/test_codex_integration.py
jleechanorg_pr_automation/tests/__init__.py
jleechanorg_pr_automation/tests/conftest.py
jleechanorg_pr_automation/tests/test_actionable_counting_matrix.py
jleechanorg_pr_automation/tests/test_atomic_race_condition.py
jleechanorg_pr_automation/tests/test_attempt_limit_logic.py
jleechanorg_pr_automation/tests/test_auto_detect_user.py
jleechanorg_pr_automation/tests/test_automation_marker_functions.py
jleechanorg_pr_automation/tests/test_automation_over_running_reproduction.py
jleechanorg_pr_automation/tests/test_automation_safety_limits.py
jleechanorg_pr_automation/tests/test_automation_safety_manager_comprehensive.py
jleechanorg_pr_automation/tests/test_cleanup_pending_reviews.py
jleechanorg_pr_automation/tests/test_cli_agent_argument.py
jleechanorg_pr_automation/tests/test_codex_actor_matching.py
jleechanorg_pr_automation/tests/test_comment_validation.py
jleechanorg_pr_automation/tests/test_concurrent_limit_one.py
jleechanorg_pr_automation-0.2.115.dist-info/METADATA
jleechanorg_pr_automation-0.2.115.dist-info/WHEEL
jleechanorg_pr_automation-0.2.115.dist-info/entry_points.txt
jleechanorg_pr_automation-0.2.115.dist-info/top_level.txt
jleechanorg_pr_automation-0.2.115.dist-info/RECORD
